tc_science/CHANGELOG.md
tc_science/LICENCE.txt
tc_science/MANIFEST.in
tc_science/README.md
tc_science/__init__.py
tc_science/requirements.txt
tc_science/setup.cfg
tc_science/setup.py
tc_science/version.py
tc_science/yproject.toml
tc_science/.git/.MERGE_MSG.swp
tc_science/.git/COMMIT_EDITMSG
tc_science/.git/FETCH_HEAD
tc_science/.git/HEAD
tc_science/.git/ORIG_HEAD
tc_science/.git/config
tc_science/.git/description
tc_science/.git/index
tc_science/.git/hooks/applypatch-msg.sample
tc_science/.git/hooks/commit-msg.sample
tc_science/.git/hooks/fsmonitor-watchman.sample
tc_science/.git/hooks/post-update.sample
tc_science/.git/hooks/pre-applypatch.sample
tc_science/.git/hooks/pre-commit.sample
tc_science/.git/hooks/pre-merge-commit.sample
tc_science/.git/hooks/pre-push.sample
tc_science/.git/hooks/pre-rebase.sample
tc_science/.git/hooks/pre-receive.sample
tc_science/.git/hooks/prepare-commit-msg.sample
tc_science/.git/hooks/push-to-checkout.sample
tc_science/.git/hooks/update.sample
tc_science/.git/info/exclude
tc_science/.git/logs/HEAD
tc_science/.git/logs/refs/heads/development
tc_science/.git/logs/refs/heads/main
tc_science/.git/logs/refs/heads/master
tc_science/.git/logs/refs/remotes/SCpackage/development
tc_science/.git/logs/refs/remotes/SCpackage/main
tc_science/.git/logs/refs/remotes/SCpackage/master
tc_science/.git/objects/00/26f736c447e99c7019666ec6d2b59320d7e3fe
tc_science/.git/objects/00/6f3730ab8c1d6c0072f802bfd4c2434bfb1d45
tc_science/.git/objects/00/7c3d8ed2ac026c5a35e3d82793a3c09afeaf86
tc_science/.git/objects/00/b38a92a0403a1183662214e598b9cf469e209c
tc_science/.git/objects/01/19b5ccc80f70c8a54e68c553e6ceb235c437b3
tc_science/.git/objects/01/436c5b25884a6823f95d38b10c88c48f9b16be
tc_science/.git/objects/01/6225c6691287146317437557328d383ed79b49
tc_science/.git/objects/01/ca9cba6824f50c82bc8b5d87fa5bf6973e3014
tc_science/.git/objects/01/d4db132af5243f26c5f9c49318f90fd110da5e
tc_science/.git/objects/02/1756d92b174510378352735f6cceda5fb7825b
tc_science/core/mat_science.egg-info/PKG-INFO
tc_science/core/mat_science.egg-info/SOURCES.txt
tc_science/core/mat_science.egg-info/dependency_links.txt
tc_science/core/mat_science.egg-info/top_level.txt
tc_science-0.1.0.dist-info/LICENSE
tc_science-0.1.0.dist-info/WHEEL
tc_science-0.1.0.dist-info/METADATA
tc_science-0.1.0.dist-info/RECORD
