Metadata-Version: 2.1
Name: tc_science
Version: 0.1.0
Summary: Use the properties of thermomechanics and set up simple chemical reactions
Author-email: Muhammed Alkohawaldeh <belalalkohawaldeh@gmail.com>
Classifier: License :: OSI Approved :: MIT License
Classifier: Development Status :: 2 - Pre-Alpha
Classifier: Intended Audience :: Science/Research
Classifier: Topic :: Scientific/Engineering :: Chemistry
Classifier: Operating System :: OS Independent
Classifier: Programming Language :: Python :: 3.10
Project-URL: Bloger, https://twisters50.blogspot.com/2023/01/python-class-objects.html
Project-URL: Dedugging, https://github.com/MASTAR-LAST/Science/issues
Project-URL: Home, https://github.com/MASTAR-LAST/Science
Project-URL: Pull_Requests, https://github.com/MASTAR-LAST/Science/pulls
